[
    {
        "id": 1,
        "parent": 0,
        "href": "/wiki/Sky",
        "children": [
            {
                "id": 56,
                "parent": 1,
                "href": "/wiki/Green",
                "children": [
                    {
                        "href": "lemon"
                    }
                ]
            },
            {
                "id": 55,
                "parent": 1,
                "href": "/wiki/Optical_phenomenon"
            },
            {
                "id": 54,
                "parent": 1,
                "href": "/wiki/Sky_brightness"
            },
            {
                "id": 53,
                "parent": 1,
                "href": "/wiki/Green_flash"
            },
            {
                "id": 52,
                "parent": 1,
                "href": "/wiki/Earth%27s_shadow"
            },
            {
                "id": 51,
                "parent": 1,
                "href": "/wiki/Overcast"
            },
            {
                "id": 50,
                "parent": 1,
                "href": "/wiki/Daylighting"
            },
            {
                "id": 49,
                "parent": 1,
                "href": "/wiki/International_Commission_on_Illumination"
            },
            {
                "id": 48,
                "parent": 1,
                "href": "/wiki/Luminance"
            },
            {
                "id": 47,
                "parent": 1,
                "href": "/wiki/Image_gradient"
            },
            {
                "id": 46,
                "parent": 1,
                "href": "/wiki/Zenith"
            },
            {
                "id": 45,
                "parent": 1,
                "href": "/wiki/Horizon"
            },
            {
                "id": 44,
                "parent": 1,
                "href": "/wiki/Polarization_(waves)"
            },
            {
                "id": 43,
                "parent": 1,
                "href": "/wiki/Optical_depth"
            },
            {
                "id": 42,
                "parent": 1,
                "href": "/wiki/Sunrise"
            },
            {
                "id": 41,
                "parent": 1,
                "href": "/wiki/Sunset"
            },
            {
                "id": 40,
                "parent": 1,
                "href": "/wiki/Visible_spectrum"
            },
            {
                "id": 39,
                "parent": 1,
                "href": "/wiki/Molecule"
            },
            {
                "id": 38,
                "parent": 1,
                "href": "/wiki/Rayleigh_Scattering"
            },
            {
                "id": 37,
                "parent": 1,
                "href": "/wiki/Diffuse_sky_radiation"
            },
            {
                "id": 36,
                "parent": 1,
                "href": "/wiki/Atmospheric_optics"
            },
            {
                "id": 35,
                "parent": 1,
                "href": "/wiki/Dawn"
            },
            {
                "id": 34,
                "parent": 1,
                "href": "/wiki/Twilight"
            },
            {
                "id": 33,
                "parent": 1,
                "href": "/wiki/City"
            },
            {
                "id": 32,
                "parent": 1,
                "href": "/wiki/Light_pollution"
            },
            {
                "id": 31,
                "parent": 1,
                "href": "/wiki/Smog"
            },
            {
                "id": 30,
                "parent": 1,
                "href": "/wiki/Flight"
            },
            {
                "id": 29,
                "parent": 1,
                "href": "/wiki/Kite_flying"
            },
            {
                "id": 28,
                "parent": 1,
                "href": "/wiki/Aircraft"
            },
            {
                "id": 27,
                "parent": 1,
                "href": "/wiki/Insect"
            },
            {
                "id": 26,
                "parent": 1,
                "href": "/wiki/Bird"
            },
            {
                "id": 25,
                "parent": 1,
                "href": "/wiki/Storm"
            },
            {
                "id": 24,
                "parent": 1,
                "href": "/wiki/Precipitation_(meteorology)"
            },
            {
                "id": 23,
                "parent": 1,
                "href": "/wiki/Lightning"
            },
            {
                "id": 22,
                "parent": 1,
                "href": "/wiki/Polar_Aurora"
            },
            {
                "id": 21,
                "parent": 1,
                "href": "/wiki/Rainbow"
            },
            {
                "id": 20,
                "parent": 1,
                "href": "/wiki/Planet"
            },
            {
                "id": 19,
                "parent": 1,
                "href": "/wiki/Moon"
            },
            {
                "id": 18,
                "parent": 1,
                "href": "/wiki/Night_sky"
            },
            {
                "id": 17,
                "parent": 1,
                "href": "/wiki/Sun"
            },
            {
                "id": 16,
                "parent": 1,
                "href": "/wiki/Star"
            },
            {
                "id": 15,
                "parent": 1,
                "href": "/wiki/Sunlight"
            },
            {
                "id": 14,
                "parent": 1,
                "href": "/wiki/Air"
            },
            {
                "id": 13,
                "parent": 1,
                "href": "/wiki/Blue"
            },
            {
                "id": 12,
                "parent": 1,
                "href": "/wiki/Daylight"
            },
            {
                "id": 11,
                "parent": 1,
                "href": "/wiki/Weather"
            },
            {
                "id": 10,
                "parent": 1,
                "href": "/wiki/Constellation"
            },
            {
                "id": 9,
                "parent": 1,
                "href": "/wiki/Celestial_sphere"
            },
            {
                "id": 8,
                "parent": 1,
                "href": "/wiki/Astronomy"
            },
            {
                "id": 7,
                "parent": 1,
                "href": "/wiki/Outer_space"
            },
            {
                "id": 6,
                "parent": 1,
                "href": "/wiki/Atmosphere_of_Earth"
            },
            {
                "id": 5,
                "parent": 1,
                "href": "/wiki/Earth"
            },
            {
                "id": 4,
                "parent": 1,
                "href": "/wiki/Cloud"
            },
            {
                "id": 3,
                "parent": 1,
                "href": "/wiki/Sky_(disambiguation)"
            },
            {
                "id": 2,
                "parent": 1,
                "href": "/wiki/Extraterrestrial_skies"
            }
        ]
    },
    {
        "id": 2,
        "parent": 1,
        "href": "/wiki/Extraterrestrial_skies"
    },
    {
        "id": 3,
        "parent": 1,
        "href": "/wiki/Sky_(disambiguation)"
    },
    {
        "id": 4,
        "parent": 1,
        "href": "/wiki/Cloud"
    },
    {
        "id": 5,
        "parent": 1,
        "href": "/wiki/Earth"
    },
    {
        "id": 6,
        "parent": 1,
        "href": "/wiki/Atmosphere_of_Earth"
    },
    {
        "id": 7,
        "parent": 1,
        "href": "/wiki/Outer_space"
    },
    {
        "id": 8,
        "parent": 1,
        "href": "/wiki/Astronomy"
    },
    {
        "id": 9,
        "parent": 1,
        "href": "/wiki/Celestial_sphere"
    },
    {
        "id": 10,
        "parent": 1,
        "href": "/wiki/Constellation"
    },
    {
        "id": 11,
        "parent": 1,
        "href": "/wiki/Weather"
    },
    {
        "id": 12,
        "parent": 1,
        "href": "/wiki/Daylight"
    },
    {
        "id": 13,
        "parent": 1,
        "href": "/wiki/Blue"
    },
    {
        "id": 14,
        "parent": 1,
        "href": "/wiki/Air"
    },
    {
        "id": 15,
        "parent": 1,
        "href": "/wiki/Sunlight"
    },
    {
        "id": 16,
        "parent": 1,
        "href": "/wiki/Star"
    },
    {
        "id": 17,
        "parent": 1,
        "href": "/wiki/Sun"
    },
    {
        "id": 18,
        "parent": 1,
        "href": "/wiki/Night_sky"
    },
    {
        "id": 19,
        "parent": 1,
        "href": "/wiki/Moon"
    },
    {
        "id": 20,
        "parent": 1,
        "href": "/wiki/Planet"
    },
    {
        "id": 21,
        "parent": 1,
        "href": "/wiki/Rainbow"
    },
    {
        "id": 22,
        "parent": 1,
        "href": "/wiki/Polar_Aurora"
    },
    {
        "id": 23,
        "parent": 1,
        "href": "/wiki/Lightning"
    },
    {
        "id": 24,
        "parent": 1,
        "href": "/wiki/Precipitation_(meteorology)"
    },
    {
        "id": 25,
        "parent": 1,
        "href": "/wiki/Storm"
    },
    {
        "id": 26,
        "parent": 1,
        "href": "/wiki/Bird"
    },
    {
        "id": 27,
        "parent": 1,
        "href": "/wiki/Insect"
    },
    {
        "id": 28,
        "parent": 1,
        "href": "/wiki/Aircraft"
    },
    {
        "id": 29,
        "parent": 1,
        "href": "/wiki/Kite_flying"
    },
    {
        "id": 30,
        "parent": 1,
        "href": "/wiki/Flight"
    },
    {
        "id": 31,
        "parent": 1,
        "href": "/wiki/Smog"
    },
    {
        "id": 32,
        "parent": 1,
        "href": "/wiki/Light_pollution"
    },
    {
        "id": 33,
        "parent": 1,
        "href": "/wiki/City"
    },
    {
        "id": 34,
        "parent": 1,
        "href": "/wiki/Twilight"
    },
    {
        "id": 35,
        "parent": 1,
        "href": "/wiki/Dawn"
    },
    {
        "id": 36,
        "parent": 1,
        "href": "/wiki/Atmospheric_optics"
    },
    {
        "id": 37,
        "parent": 1,
        "href": "/wiki/Diffuse_sky_radiation"
    },
    {
        "id": 38,
        "parent": 1,
        "href": "/wiki/Rayleigh_Scattering"
    },
    {
        "id": 39,
        "parent": 1,
        "href": "/wiki/Molecule"
    },
    {
        "id": 40,
        "parent": 1,
        "href": "/wiki/Visible_spectrum"
    },
    {
        "id": 41,
        "parent": 1,
        "href": "/wiki/Sunset"
    },
    {
        "id": 42,
        "parent": 1,
        "href": "/wiki/Sunrise"
    },
    {
        "id": 43,
        "parent": 1,
        "href": "/wiki/Optical_depth"
    },
    {
        "id": 44,
        "parent": 1,
        "href": "/wiki/Polarization_(waves)"
    },
    {
        "id": 45,
        "parent": 1,
        "href": "/wiki/Horizon"
    },
    {
        "id": 46,
        "parent": 1,
        "href": "/wiki/Zenith"
    },
    {
        "id": 47,
        "parent": 1,
        "href": "/wiki/Image_gradient"
    },
    {
        "id": 48,
        "parent": 1,
        "href": "/wiki/Luminance"
    },
    {
        "id": 49,
        "parent": 1,
        "href": "/wiki/International_Commission_on_Illumination"
    },
    {
        "id": 50,
        "parent": 1,
        "href": "/wiki/Daylighting"
    },
    {
        "id": 51,
        "parent": 1,
        "href": "/wiki/Overcast"
    },
    {
        "id": 52,
        "parent": 1,
        "href": "/wiki/Earth%27s_shadow"
    },
    {
        "id": 53,
        "parent": 1,
        "href": "/wiki/Green_flash"
    },
    {
        "id": 54,
        "parent": 1,
        "href": "/wiki/Sky_brightness"
    },
    {
        "id": 55,
        "parent": 1,
        "href": "/wiki/Optical_phenomenon"
    },
    {
        "id": 56,
        "parent": 1,
        "href": "/wiki/Green",
        "children": [
            {
                "href": "lemon"
            }
        ]
    }
]